Metadata-Version: 2.1
Name: apereocla
Version: 2
Summary: Easy access to list of completed Apereo CLAs
Home-page: https://github.com/lkiesow/python-apereocla
Author: Lars Kiesow
Author-email: lkiesow@uos.de
License: MIT
License-File: LICENSE
Requires-Dist: requests
Requires-Dist: beautifulsoup4
